{"test.md":"7uKBWmg_","ea-link.md":"DQR_AFmP","ea-checkbox.md":"CJDKvWuZ","index.md":"BRYLn-EI","ea-nav-menu.md":"BVb18unk","ea-progress.md":"_X9Mx8Wy","ea-input-number.md":"Bqp4Ivsm","ea-drawer.md":"DERqODlY","ea-rate.md":"DJPiqiK7","ea-empty.md":"zBE_HzVs","ea-avatar.md":"CaSoKfxc","ea-pagination.md":"Bvy9XJfD","ea-button.md":"Dwnbv03U","ea-result.md":"BhNM76YT","ea-badge.md":"O3dmE1JU","ea-backtop.md":"DllO-Vr7","ea-icon.md":"895eJ4Kv","ea-switch.md":"Dylx0fox","ea-descriptions.md":"CqrT0AAq","ea-skeleton.md":"y2W8JAoY","ea-infinite-scroll.md":"Bdxn2AXV","ea-message-box.md":"B1doeHkr","ea-radio.md":"D2rem6D4","example.md":"CY45nbnI","ea-timeline.md":"l_LkaIr1","ea-alert.md":"cVrszLb6","ea-tag.md":"5_TKt7eC","ea-textarea.md":"CQubmTRy","ea-breadcrumb.md":"SR0QQQmW","ea-form.md":"CIGVKdXG","ea-time-picker.md":"C43kq5wx","ea-page-header.md":"COAHMept","ea-date-picker.md":"Czjms-tu","ea-card.md":"DCOsvII6","install.md":"D1pCrQm8","ea-image.md":"6HkK4DnN","ea-collapse.md":"CEfFwNhJ","ea-tabs.md":"BKGHidn9","ea-calendar.md":"BChyDbhC","ea-carousel.md":"Cre2BPC1","ea-container.md":"C9y5ufsX","ea-loading.md":"CgsHftdA","ea-steps.md":"C8IDJt_V","ea-table.md":"CsXsLuYT","ea-message.md":"op0XR0J7","ea-select.md":"CnflAoMU","ea-input.md":"D9KY_my5"}
